{
    "metadata": {
        "timestamp": "2025-03-03T09:21:54.517046",
        "n_nodes": 58,
        "max_resources": 8
    },
    "graph": {
        "nodes": [
            {
                "id": 0,
                "x": 75.99133216468643,
                "y": 35.759221258542254
            },
            {
                "id": 1,
                "x": 49.04746365811158,
                "y": 43.51184224611967
            },
            {
                "id": 2,
                "x": 54.0807496877015,
                "y": 95.79642694563744
            },
            {
                "id": 3,
                "x": 97.1499084896926,
                "y": 52.86826150491565
            },
            {
                "id": 4,
                "x": 81.28495036452881,
                "y": 96.65603786839483
            },
            {
                "id": 5,
                "x": 49.92478022572892,
                "y": 97.18509465332552
            },
            {
                "id": 6,
                "x": 24.4696864780789,
                "y": 30.218146414131564
            },
            {
                "id": 7,
                "x": 71.69484981023612,
                "y": 7.018293337027181
            },
            {
                "id": 8,
                "x": 68.80751627065281,
                "y": 45.281863739101745
            },
            {
                "id": 9,
                "x": 67.6208085969053,
                "y": 52.6304624938098
            },
            {
                "id": 10,
                "x": 16.93182201172616,
                "y": 49.01961838456903
            },
            {
                "id": 11,
                "x": 54.41971626383882,
                "y": 43.670897293035274
            },
            {
                "id": 12,
                "x": 0.33031344694816056,
                "y": 85.19171569286719
            },
            {
                "id": 13,
                "x": 38.8310353687671,
                "y": 7.879559765256516
            },
            {
                "id": 14,
                "x": 95.95627508662545,
                "y": 5.930191437632459
            },
            {
                "id": 15,
                "x": 96.73033144202229,
                "y": 94.16535634670953
            },
            {
                "id": 16,
                "x": 73.62429020016421,
                "y": 42.70660154814766
            },
            {
                "id": 17,
                "x": 17.75286529347886,
                "y": 56.876682360828354
            },
            {
                "id": 18,
                "x": 51.78351013454522,
                "y": 47.81501007010293
            },
            {
                "id": 19,
                "x": 22.69550607685019,
                "y": 68.57812324637028
            },
            {
                "id": 20,
                "x": 17.136072346021724,
                "y": 49.98019137714298
            },
            {
                "id": 21,
                "x": 77.79532999139866,
                "y": 74.47452148649002
            },
            {
                "id": 22,
                "x": 55.112941793803216,
                "y": 3.2255967298836064
            },
            {
                "id": 23,
                "x": 37.14987168932409,
                "y": 84.88970261670842
            },
            {
                "id": 24,
                "x": 14.141661301500275,
                "y": 42.58889661642426
            },
            {
                "id": 25,
                "x": 10.834865017295837,
                "y": 52.82183864103697
            },
            {
                "id": 26,
                "x": 21.90944868175817,
                "y": 36.05181001644369
            },
            {
                "id": 27,
                "x": 36.67021930290031,
                "y": 80.90298835871693
            },
            {
                "id": 28,
                "x": 5.384211864058752,
                "y": 83.52790317234651
            },
            {
                "id": 29,
                "x": 27.478937292758697,
                "y": 58.049981651879655
            },
            {
                "id": 30,
                "x": 30.796510265925193,
                "y": 54.16960848288809
            },
            {
                "id": 31,
                "x": 81.2587360098636,
                "y": 50.52236426155615
            },
            {
                "id": 32,
                "x": 82.59301358479769,
                "y": 48.29867957050325
            },
            {
                "id": 33,
                "x": 36.09622377147497,
                "y": 64.2908157740153
            },
            {
                "id": 34,
                "x": 16.960641052694125,
                "y": 52.42010648679754
            },
            {
                "id": 35,
                "x": 62.675708804609066,
                "y": 95.37006307390418
            },
            {
                "id": 36,
                "x": 0.98762027570235,
                "y": 52.28382778277333
            },
            {
                "id": 37,
                "x": 18.055741562547688,
                "y": 43.7622086910608
            },
            {
                "id": 38,
                "x": 6.219288663287448,
                "y": 90.81015706651878
            },
            {
                "id": 39,
                "x": 42.89198584918702,
                "y": 11.56727460611824
            },
            {
                "id": 40,
                "x": 73.69490104167976,
                "y": 31.012170845151143
            },
            {
                "id": 41,
                "x": 55.86533586773441,
                "y": 21.32157278499397
            },
            {
                "id": 42,
                "x": 14.726601880525314,
                "y": 66.3019145194807
            },
            {
                "id": 43,
                "x": 9.699935823748273,
                "y": 16.60335156824706
            },
            {
                "id": 44,
                "x": 90.25698087370559,
                "y": 61.39652062267006
            },
            {
                "id": 45,
                "x": 53.58493780696381,
                "y": 56.61359323644284
            },
            {
                "id": 46,
                "x": 59.283189475810595,
                "y": 31.651666680319668
            },
            {
                "id": 47,
                "x": 42.55364172276924,
                "y": 71.57996148711948
            },
            {
                "id": 48,
                "x": 51.389522521922245,
                "y": 70.29891654829295
            },
            {
                "id": 49,
                "x": 59.400770389755934,
                "y": 72.54597455565464
            },
            {
                "id": 50,
                "x": 56.497175110140404,
                "y": 13.255847134709775
            },
            {
                "id": 51,
                "x": 61.332360255976695,
                "y": 14.247998467533451
            },
            {
                "id": 52,
                "x": 5.979807104413615,
                "y": 12.98004715839306
            },
            {
                "id": 53,
                "x": 32.40341420101619,
                "y": 77.7564890918896
            },
            {
                "id": 54,
                "x": 26.383213546391005,
                "y": 46.05197411391523
            },
            {
                "id": 55,
                "x": 64.15680038476437,
                "y": 58.22754019666437
            },
            {
                "id": 56,
                "x": 87.8701774572439,
                "y": 99.51383493948998
            },
            {
                "id": 57,
                "x": 87.01190489520204,
                "y": 58.34113233433561
            }
        ],
        "edges": [
            {
                "source": 0,
                "target": 40,
                "weight": 5.273337039294037
            },
            {
                "source": 0,
                "target": 16,
                "weight": 7.339549069950202
            },
            {
                "source": 0,
                "target": 8,
                "weight": 11.92845046986096
            },
            {
                "source": 1,
                "target": 18,
                "weight": 5.099333646916009
            },
            {
                "source": 1,
                "target": 11,
                "weight": 5.374606643066304
            },
            {
                "source": 1,
                "target": 45,
                "weight": 13.865228114385149
            },
            {
                "source": 2,
                "target": 5,
                "weight": 4.3818352514927295
            },
            {
                "source": 2,
                "target": 35,
                "weight": 8.605527780004657
            },
            {
                "source": 2,
                "target": 23,
                "weight": 20.13979308193588
            },
            {
                "source": 3,
                "target": 44,
                "weight": 10.965566775082705
            },
            {
                "source": 3,
                "target": 57,
                "weight": 11.520912810946
            },
            {
                "source": 3,
                "target": 32,
                "weight": 15.257269360126791
            },
            {
                "source": 4,
                "target": 56,
                "weight": 7.1785945673362
            },
            {
                "source": 4,
                "target": 15,
                "weight": 15.644912625881242
            },
            {
                "source": 4,
                "target": 35,
                "weight": 18.653621702165765
            },
            {
                "source": 5,
                "target": 35,
                "weight": 12.879461140047718
            },
            {
                "source": 5,
                "target": 23,
                "weight": 17.73062191372926
            },
            {
                "source": 6,
                "target": 26,
                "weight": 6.370749453451336
            },
            {
                "source": 6,
                "target": 37,
                "weight": 14.986003881649244
            },
            {
                "source": 6,
                "target": 54,
                "weight": 15.949033997944815
            },
            {
                "source": 6,
                "target": 43,
                "weight": 20.087512864628692
            },
            {
                "source": 6,
                "target": 52,
                "weight": 25.278997314042844
            },
            {
                "source": 7,
                "target": 51,
                "weight": 12.635261217569045
            },
            {
                "source": 7,
                "target": 50,
                "weight": 16.427915073706522
            },
            {
                "source": 7,
                "target": 22,
                "weight": 17.010121134762098
            },
            {
                "source": 7,
                "target": 14,
                "weight": 24.285813187647015
            },
            {
                "source": 8,
                "target": 16,
                "weight": 5.4619855767091074
            },
            {
                "source": 8,
                "target": 9,
                "weight": 7.443801364936334
            },
            {
                "source": 8,
                "target": 55,
                "weight": 13.75571507393005
            },
            {
                "source": 9,
                "target": 55,
                "weight": 6.582296841192416
            },
            {
                "source": 9,
                "target": 16,
                "weight": 11.598482979661883
            },
            {
                "source": 10,
                "target": 20,
                "weight": 0.9820482030543738
            },
            {
                "source": 10,
                "target": 34,
                "weight": 3.4006102203163477
            },
            {
                "source": 10,
                "target": 37,
                "weight": 5.376202362459319
            },
            {
                "source": 10,
                "target": 17,
                "weight": 7.899845973026515
            },
            {
                "source": 10,
                "target": 24,
                "weight": 7.0099343255254
            },
            {
                "source": 10,
                "target": 25,
                "weight": 7.1853854086352245
            },
            {
                "source": 10,
                "target": 36,
                "weight": 16.274908048721812
            },
            {
                "source": 10,
                "target": 54,
                "weight": 9.906347180403007
            },
            {
                "source": 11,
                "target": 18,
                "weight": 4.911542880315773
            },
            {
                "source": 11,
                "target": 46,
                "weight": 12.965927510410006
            },
            {
                "source": 11,
                "target": 45,
                "weight": 12.96958878899255
            },
            {
                "source": 12,
                "target": 28,
                "weight": 5.320729396794609
            },
            {
                "source": 12,
                "target": 38,
                "weight": 8.139220636388863
            },
            {
                "source": 12,
                "target": 42,
                "weight": 23.750320188006327
            },
            {
                "source": 13,
                "target": 39,
                "weight": 5.485486263945488
            },
            {
                "source": 13,
                "target": 22,
                "weight": 16.933985023267557
            },
            {
                "source": 13,
                "target": 50,
                "weight": 18.466102979261
            },
            {
                "source": 14,
                "target": 40,
                "weight": 33.536166527618704
            },
            {
                "source": 14,
                "target": 51,
                "weight": 35.60900717496473
            },
            {
                "source": 15,
                "target": 56,
                "weight": 10.349326156393719
            },
            {
                "source": 15,
                "target": 21,
                "weight": 27.31781941201667
            },
            {
                "source": 16,
                "target": 32,
                "weight": 10.56926372829176
            },
            {
                "source": 16,
                "target": 31,
                "weight": 10.925699502253526
            },
            {
                "source": 16,
                "target": 40,
                "weight": 11.694643874788456
            },
            {
                "source": 17,
                "target": 34,
                "weight": 4.526443169717304
            },
            {
                "source": 17,
                "target": 20,
                "weight": 6.924017722976057
            },
            {
                "source": 17,
                "target": 19,
                "weight": 12.70249647554676
            },
            {
                "source": 17,
                "target": 29,
                "weight": 9.796586536215397
            },
            {
                "source": 17,
                "target": 42,
                "weight": 9.899155089656675
            },
            {
                "source": 18,
                "target": 45,
                "weight": 8.981102793864208
            },
            {
                "source": 19,
                "target": 42,
                "weight": 8.28761487151596
            },
            {
                "source": 19,
                "target": 29,
                "weight": 11.563865254791393
            },
            {
                "source": 20,
                "target": 34,
                "weight": 2.446213784810975
            },
            {
                "source": 20,
                "target": 37,
                "weight": 6.285626472535832
            },
            {
                "source": 20,
                "target": 24,
                "weight": 7.974818853327019
            },
            {
                "source": 20,
                "target": 25,
                "weight": 6.912320375386621
            },
            {
                "source": 21,
                "target": 44,
                "weight": 18.064519072108634
            },
            {
                "source": 21,
                "target": 49,
                "weight": 18.495380942354803
            },
            {
                "source": 21,
                "target": 57,
                "weight": 18.58040630589847
            },
            {
                "source": 22,
                "target": 50,
                "weight": 10.125316047293209
            },
            {
                "source": 22,
                "target": 51,
                "weight": 12.656006719094716
            },
            {
                "source": 22,
                "target": 39,
                "weight": 14.796464239510472
            },
            {
                "source": 23,
                "target": 27,
                "weight": 4.015464728605481
            },
            {
                "source": 23,
                "target": 53,
                "weight": 8.568056598726
            },
            {
                "source": 23,
                "target": 47,
                "weight": 14.364885642114643
            },
            {
                "source": 24,
                "target": 37,
                "weight": 4.086157793625803
            },
            {
                "source": 24,
                "target": 26,
                "weight": 10.152439214323785
            },
            {
                "source": 25,
                "target": 34,
                "weight": 6.13893482288335
            },
            {
                "source": 25,
                "target": 36,
                "weight": 9.861931082929456
            },
            {
                "source": 25,
                "target": 42,
                "weight": 14.030611586856072
            },
            {
                "source": 26,
                "target": 37,
                "weight": 8.61982054814315
            },
            {
                "source": 26,
                "target": 43,
                "weight": 22.96333469340069
            },
            {
                "source": 26,
                "target": 52,
                "weight": 28.036756626985028
            },
            {
                "source": 27,
                "target": 53,
                "weight": 5.301517086043314
            },
            {
                "source": 27,
                "target": 47,
                "weight": 11.02422284876102
            },
            {
                "source": 28,
                "target": 38,
                "weight": 7.329977833513363
            },
            {
                "source": 28,
                "target": 42,
                "weight": 19.596299045698288
            },
            {
                "source": 29,
                "target": 30,
                "weight": 5.1052508618984085
            },
            {
                "source": 29,
                "target": 33,
                "weight": 10.639813757593638
            },
            {
                "source": 30,
                "target": 54,
                "weight": 9.239760585804191
            },
            {
                "source": 30,
                "target": 33,
                "weight": 11.424788850165823
            },
            {
                "source": 31,
                "target": 32,
                "weight": 2.5932740410907233
            },
            {
                "source": 31,
                "target": 57,
                "weight": 9.707321278248795
            },
            {
                "source": 31,
                "target": 44,
                "weight": 14.114378739271979
            },
            {
                "source": 32,
                "target": 57,
                "weight": 10.971666141793198
            },
            {
                "source": 33,
                "target": 47,
                "weight": 9.738064069647649
            },
            {
                "source": 34,
                "target": 36,
                "weight": 15.973602118100397
            },
            {
                "source": 35,
                "target": 56,
                "weight": 25.532960971313525
            },
            {
                "source": 37,
                "target": 54,
                "weight": 8.636539546218444
            },
            {
                "source": 38,
                "target": 42,
                "weight": 25.94278957476697
            },
            {
                "source": 39,
                "target": 50,
                "weight": 13.709575194391517
            },
            {
                "source": 40,
                "target": 46,
                "weight": 14.425892872921414
            },
            {
                "source": 41,
                "target": 50,
                "weight": 8.090435778985984
            },
            {
                "source": 41,
                "target": 51,
                "weight": 8.940011705041162
            },
            {
                "source": 41,
                "target": 46,
                "weight": 10.880834672601393
            },
            {
                "source": 43,
                "target": 52,
                "weight": 5.193042704897195
            },
            {
                "source": 44,
                "target": 57,
                "weight": 4.457119663948017
            },
            {
                "source": 45,
                "target": 55,
                "weight": 10.694349122518313
            },
            {
                "source": 45,
                "target": 48,
                "weight": 13.860300228482146
            },
            {
                "source": 47,
                "target": 48,
                "weight": 8.928262184329814
            },
            {
                "source": 47,
                "target": 49,
                "weight": 16.87480149722021
            },
            {
                "source": 47,
                "target": 53,
                "weight": 11.8817764663303
            },
            {
                "source": 48,
                "target": 49,
                "weight": 8.320418384211102
            },
            {
                "source": 49,
                "target": 55,
                "weight": 15.087656670475138
            },
            {
                "source": 50,
                "target": 51,
                "weight": 4.935927436838969
            }
        ]
    },
    "configuration": {
        "start_node": 43,
        "extraction_nodes": [
            23,
            37
        ]
    }
}