{
    "metadata": {
        "timestamp": "2025-03-03T09:22:00.298496",
        "n_nodes": 58,
        "max_resources": 17
    },
    "graph": {
        "nodes": [
            {
                "id": 0,
                "x": 87.46762669834114,
                "y": 81.24311396349412
            },
            {
                "id": 1,
                "x": 2.582833261481443,
                "y": 47.449241524617634
            },
            {
                "id": 2,
                "x": 70.09180791979863,
                "y": 73.48266073531589
            },
            {
                "id": 3,
                "x": 47.834678620219904,
                "y": 38.356551257207215
            },
            {
                "id": 4,
                "x": 61.89438659983524,
                "y": 33.644081797965754
            },
            {
                "id": 5,
                "x": 54.14238911236341,
                "y": 8.57481951125033
            },
            {
                "id": 6,
                "x": 2.4792114679318633,
                "y": 44.76227458545948
            },
            {
                "id": 7,
                "x": 71.19173775987977,
                "y": 56.000817775334156
            },
            {
                "id": 8,
                "x": 75.12443406380164,
                "y": 18.186279429805364
            },
            {
                "id": 9,
                "x": 33.817769872068794,
                "y": 68.82936956811527
            },
            {
                "id": 10,
                "x": 95.30245908377233,
                "y": 9.213985467634412
            },
            {
                "id": 11,
                "x": 5.101484308597371,
                "y": 82.22749319438402
            },
            {
                "id": 12,
                "x": 56.3137813826455,
                "y": 1.2635648888609907
            },
            {
                "id": 13,
                "x": 74.4242791541914,
                "y": 40.19897325848799
            },
            {
                "id": 14,
                "x": 82.21270673375204,
                "y": 42.755233520348256
            },
            {
                "id": 15,
                "x": 52.49430294859218,
                "y": 23.684175592870183
            },
            {
                "id": 16,
                "x": 25.361676688253855,
                "y": 32.45702212221779
            },
            {
                "id": 17,
                "x": 42.16682604152127,
                "y": 72.52486600916282
            },
            {
                "id": 18,
                "x": 14.992652126113748,
                "y": 64.73697641770522
            },
            {
                "id": 19,
                "x": 92.86973333327445,
                "y": 21.87513621525796
            },
            {
                "id": 20,
                "x": 67.78929596023201,
                "y": 20.011208116979585
            },
            {
                "id": 21,
                "x": 60.75432340380529,
                "y": 21.829917261940125
            },
            {
                "id": 22,
                "x": 76.00139147219667,
                "y": 38.23845407962436
            },
            {
                "id": 23,
                "x": 42.503484908110536,
                "y": 30.28405735224924
            },
            {
                "id": 24,
                "x": 59.04913823408475,
                "y": 57.32232922516556
            },
            {
                "id": 25,
                "x": 83.2312440134795,
                "y": 25.819605049670724
            },
            {
                "id": 26,
                "x": 45.82764342672658,
                "y": 84.07926067228819
            },
            {
                "id": 27,
                "x": 67.02861869817343,
                "y": 11.682412161936185
            },
            {
                "id": 28,
                "x": 36.90564365158148,
                "y": 30.40909968306621
            },
            {
                "id": 29,
                "x": 54.349015458318085,
                "y": 72.80048219675929
            },
            {
                "id": 30,
                "x": 74.49872479427174,
                "y": 50.80248423776374
            },
            {
                "id": 31,
                "x": 99.33589004187016,
                "y": 52.18333750466542
            },
            {
                "id": 32,
                "x": 3.1835289917744647,
                "y": 17.66519828863895
            },
            {
                "id": 33,
                "x": 26.60416638958958,
                "y": 46.355958882975216
            },
            {
                "id": 34,
                "x": 89.24220169213524,
                "y": 74.3400081241316
            },
            {
                "id": 35,
                "x": 77.95335518776258,
                "y": 92.94100296569195
            },
            {
                "id": 36,
                "x": 9.722291584098585,
                "y": 3.5482176203646687
            },
            {
                "id": 37,
                "x": 85.25211353536004,
                "y": 33.285189700860464
            },
            {
                "id": 38,
                "x": 20.53775698807031,
                "y": 1.8077037735697687
            },
            {
                "id": 39,
                "x": 97.78356722981947,
                "y": 72.75510837655689
            },
            {
                "id": 40,
                "x": 26.149332541147153,
                "y": 87.22578613050871
            },
            {
                "id": 41,
                "x": 11.073652571787552,
                "y": 53.606809818233614
            },
            {
                "id": 42,
                "x": 31.278520544160095,
                "y": 60.64251272827956
            },
            {
                "id": 43,
                "x": 91.48616768568606,
                "y": 35.53935479364259
            },
            {
                "id": 44,
                "x": 27.131694810319406,
                "y": 81.24719684054455
            },
            {
                "id": 45,
                "x": 28.299514474760233,
                "y": 76.43911833898389
            },
            {
                "id": 46,
                "x": 95.53447904065533,
                "y": 91.40677417118253
            },
            {
                "id": 47,
                "x": 67.97971599060637,
                "y": 71.03923515719701
            },
            {
                "id": 48,
                "x": 4.145306087096589,
                "y": 2.7288304430271415
            },
            {
                "id": 49,
                "x": 67.86470792332663,
                "y": 72.25843659391849
            },
            {
                "id": 50,
                "x": 87.17966110663696,
                "y": 65.853670510217
            },
            {
                "id": 51,
                "x": 14.439332078242039,
                "y": 77.17700234541178
            },
            {
                "id": 52,
                "x": 16.33801656645135,
                "y": 65.68193608207164
            },
            {
                "id": 53,
                "x": 47.3221350396957,
                "y": 78.67266258955364
            },
            {
                "id": 54,
                "x": 26.482816749638328,
                "y": 4.785639109721462
            },
            {
                "id": 55,
                "x": 39.51768764993516,
                "y": 8.61977850990241
            },
            {
                "id": 56,
                "x": 57.7142667442692,
                "y": 63.18259164420104
            },
            {
                "id": 57,
                "x": 64.379498997916,
                "y": 67.22674820251248
            }
        ],
        "edges": [
            {
                "source": 0,
                "target": 34,
                "weight": 7.1275512371389045
            },
            {
                "source": 0,
                "target": 46,
                "weight": 12.975904420503749
            },
            {
                "source": 0,
                "target": 39,
                "weight": 13.359074365122577
            },
            {
                "source": 0,
                "target": 35,
                "weight": 15.07852676771665
            },
            {
                "source": 0,
                "target": 50,
                "weight": 15.392137407898218
            },
            {
                "source": 1,
                "target": 6,
                "weight": 2.688964263099711
            },
            {
                "source": 1,
                "target": 41,
                "weight": 10.488548986910054
            },
            {
                "source": 1,
                "target": 18,
                "weight": 21.280727947762077
            },
            {
                "source": 2,
                "target": 49,
                "weight": 2.5413970848070453
            },
            {
                "source": 2,
                "target": 47,
                "weight": 3.22974625522883
            },
            {
                "source": 2,
                "target": 57,
                "weight": 8.471535565474925
            },
            {
                "source": 2,
                "target": 35,
                "weight": 20.986448194033883
            },
            {
                "source": 3,
                "target": 23,
                "weight": 9.67402626839612
            },
            {
                "source": 3,
                "target": 28,
                "weight": 13.513171051571792
            },
            {
                "source": 3,
                "target": 4,
                "weight": 14.828444182595238
            },
            {
                "source": 4,
                "target": 21,
                "weight": 11.869044939472918
            },
            {
                "source": 4,
                "target": 15,
                "weight": 13.695302269927023
            },
            {
                "source": 4,
                "target": 13,
                "weight": 14.140891396334858
            },
            {
                "source": 5,
                "target": 12,
                "weight": 7.626885900867425
            },
            {
                "source": 5,
                "target": 27,
                "weight": 13.255642007115394
            },
            {
                "source": 5,
                "target": 55,
                "weight": 14.624770568344337
            },
            {
                "source": 6,
                "target": 41,
                "weight": 12.3324864229168
            },
            {
                "source": 6,
                "target": 18,
                "weight": 23.570636614078985
            },
            {
                "source": 7,
                "target": 30,
                "weight": 6.161074160685448
            },
            {
                "source": 7,
                "target": 24,
                "weight": 12.214299642463049
            },
            {
                "source": 7,
                "target": 57,
                "weight": 13.131188480326136
            },
            {
                "source": 8,
                "target": 20,
                "weight": 7.558744321096629
            },
            {
                "source": 8,
                "target": 27,
                "weight": 10.3847251226213
            },
            {
                "source": 8,
                "target": 25,
                "weight": 11.134991135114959
            },
            {
                "source": 8,
                "target": 10,
                "weight": 22.082906345184107
            },
            {
                "source": 9,
                "target": 42,
                "weight": 8.571604987705014
            },
            {
                "source": 9,
                "target": 17,
                "weight": 9.13035776223843
            },
            {
                "source": 9,
                "target": 45,
                "weight": 9.399969094931192
            },
            {
                "source": 10,
                "target": 19,
                "weight": 12.892745744455825
            },
            {
                "source": 10,
                "target": 25,
                "weight": 20.52951131850373
            },
            {
                "source": 11,
                "target": 51,
                "weight": 10.616160265586155
            },
            {
                "source": 11,
                "target": 52,
                "weight": 20.000377929893823
            },
            {
                "source": 11,
                "target": 18,
                "weight": 20.09361535188614
            },
            {
                "source": 12,
                "target": 27,
                "weight": 14.94523727472723
            },
            {
                "source": 12,
                "target": 55,
                "weight": 18.336374873905335
            },
            {
                "source": 13,
                "target": 22,
                "weight": 2.516131696532614
            },
            {
                "source": 13,
                "target": 14,
                "weight": 8.197198953815068
            },
            {
                "source": 13,
                "target": 30,
                "weight": 10.603772311821318
            },
            {
                "source": 14,
                "target": 22,
                "weight": 7.679956627128614
            },
            {
                "source": 14,
                "target": 37,
                "weight": 9.945839514524646
            },
            {
                "source": 14,
                "target": 30,
                "weight": 11.147365674076203
            },
            {
                "source": 14,
                "target": 31,
                "weight": 19.547187811614027
            },
            {
                "source": 14,
                "target": 43,
                "weight": 11.750148246961325
            },
            {
                "source": 15,
                "target": 21,
                "weight": 8.465589871849598
            },
            {
                "source": 15,
                "target": 23,
                "weight": 11.973925185827653
            },
            {
                "source": 16,
                "target": 28,
                "weight": 11.72421253505668
            },
            {
                "source": 16,
                "target": 33,
                "weight": 13.954362175945533
            },
            {
                "source": 16,
                "target": 23,
                "weight": 17.278986224251426
            },
            {
                "source": 17,
                "target": 53,
                "weight": 8.02325455538607
            },
            {
                "source": 17,
                "target": 26,
                "weight": 12.12046286076078
            },
            {
                "source": 18,
                "target": 52,
                "weight": 1.6440663747563273
            },
            {
                "source": 18,
                "target": 41,
                "weight": 11.799964662608202
            },
            {
                "source": 18,
                "target": 51,
                "weight": 12.452325411640516
            },
            {
                "source": 19,
                "target": 25,
                "weight": 10.414379998514315
            },
            {
                "source": 19,
                "target": 37,
                "weight": 13.7192365651259
            },
            {
                "source": 20,
                "target": 21,
                "weight": 7.266260511682762
            },
            {
                "source": 20,
                "target": 27,
                "weight": 8.36346052527064
            },
            {
                "source": 21,
                "target": 27,
                "weight": 11.930575895384774
            },
            {
                "source": 22,
                "target": 37,
                "weight": 10.49336393611833
            },
            {
                "source": 23,
                "target": 28,
                "weight": 5.599237655055817
            },
            {
                "source": 24,
                "target": 56,
                "weight": 6.010370830013898
            },
            {
                "source": 24,
                "target": 57,
                "weight": 11.247678033773083
            },
            {
                "source": 25,
                "target": 37,
                "weight": 7.734265822206107
            },
            {
                "source": 25,
                "target": 43,
                "weight": 12.75214883536878
            },
            {
                "source": 26,
                "target": 53,
                "weight": 5.609350052320138
            },
            {
                "source": 26,
                "target": 29,
                "weight": 14.13593382839789
            },
            {
                "source": 29,
                "target": 53,
                "weight": 9.15748606240474
            },
            {
                "source": 29,
                "target": 56,
                "weight": 10.189638604905717
            },
            {
                "source": 29,
                "target": 57,
                "weight": 11.475064735188521
            },
            {
                "source": 31,
                "target": 50,
                "weight": 18.29349355395174
            },
            {
                "source": 31,
                "target": 43,
                "weight": 18.402181978069972
            },
            {
                "source": 32,
                "target": 48,
                "weight": 14.967301012557762
            },
            {
                "source": 32,
                "target": 36,
                "weight": 15.557781314416495
            },
            {
                "source": 32,
                "target": 38,
                "weight": 23.508070138632558
            },
            {
                "source": 33,
                "target": 42,
                "weight": 15.031806529393966
            },
            {
                "source": 33,
                "target": 41,
                "weight": 17.1397695063346
            },
            {
                "source": 34,
                "target": 39,
                "weight": 8.687164811271982
            },
            {
                "source": 34,
                "target": 50,
                "weight": 8.733384210268625
            },
            {
                "source": 34,
                "target": 46,
                "weight": 18.189756939977773
            },
            {
                "source": 35,
                "target": 46,
                "weight": 17.64793965098068
            },
            {
                "source": 36,
                "target": 48,
                "weight": 5.636857509300351
            },
            {
                "source": 36,
                "target": 38,
                "weight": 10.95461913328775
            },
            {
                "source": 36,
                "target": 54,
                "weight": 16.806142203581793
            },
            {
                "source": 37,
                "target": 43,
                "weight": 6.629079228272541
            },
            {
                "source": 38,
                "target": 54,
                "weight": 6.649198029455588
            },
            {
                "source": 38,
                "target": 48,
                "weight": 16.418310536776303
            },
            {
                "source": 39,
                "target": 50,
                "weight": 12.651982836386463
            },
            {
                "source": 40,
                "target": 44,
                "weight": 6.058759404859005
            },
            {
                "source": 40,
                "target": 45,
                "weight": 10.998885597748302
            },
            {
                "source": 40,
                "target": 51,
                "weight": 15.430559497337255
            },
            {
                "source": 41,
                "target": 52,
                "weight": 13.172782642856578
            },
            {
                "source": 42,
                "target": 52,
                "weight": 15.767512386127237
            },
            {
                "source": 44,
                "target": 45,
                "weight": 4.947870415221529
            },
            {
                "source": 44,
                "target": 51,
                "weight": 13.32901177697865
            },
            {
                "source": 47,
                "target": 49,
                "weight": 1.2246138162062081
            },
            {
                "source": 47,
                "target": 57,
                "weight": 5.243721881840814
            },
            {
                "source": 49,
                "target": 57,
                "weight": 6.120830770571255
            },
            {
                "source": 51,
                "target": 52,
                "weight": 11.650817618705874
            },
            {
                "source": 54,
                "target": 55,
                "weight": 13.587070483640877
            },
            {
                "source": 56,
                "target": 57,
                "weight": 7.796186456414896
            }
        ]
    },
    "configuration": {
        "start_node": 17,
        "extraction_nodes": [
            37,
            3
        ]
    }
}