{
    "metadata": {
        "timestamp": "2025-03-03T09:21:52.170638",
        "n_nodes": 52,
        "max_resources": 15
    },
    "graph": {
        "nodes": [
            {
                "id": 0,
                "x": 92.68405495187467,
                "y": 75.60936995848651
            },
            {
                "id": 1,
                "x": 89.19778396543992,
                "y": 61.923290450588475
            },
            {
                "id": 2,
                "x": 67.58633711553236,
                "y": 0.4037154030393064
            },
            {
                "id": 3,
                "x": 94.70167910419316,
                "y": 24.876899643083572
            },
            {
                "id": 4,
                "x": 33.66551464175602,
                "y": 76.35119655491913
            },
            {
                "id": 5,
                "x": 31.23132976513797,
                "y": 6.828941983251857
            },
            {
                "id": 6,
                "x": 45.64931194897392,
                "y": 92.87308848006283
            },
            {
                "id": 7,
                "x": 62.14324832721546,
                "y": 59.216987051946525
            },
            {
                "id": 8,
                "x": 86.27269451526992,
                "y": 93.9044108692923
            },
            {
                "id": 9,
                "x": 33.608143395194354,
                "y": 75.06362109179963
            },
            {
                "id": 10,
                "x": 37.86951074269712,
                "y": 59.54192228180153
            },
            {
                "id": 11,
                "x": 11.789946701711118,
                "y": 7.080732922818644
            },
            {
                "id": 12,
                "x": 5.138277375621292,
                "y": 66.24987408042985
            },
            {
                "id": 13,
                "x": 32.51485134022717,
                "y": 56.903978034030665
            },
            {
                "id": 14,
                "x": 89.6889962739141,
                "y": 57.306730242542024
            },
            {
                "id": 15,
                "x": 0.9034025608180563,
                "y": 71.04048178219495
            },
            {
                "id": 16,
                "x": 77.79103717912274,
                "y": 59.71047950644047
            },
            {
                "id": 17,
                "x": 47.02260585743755,
                "y": 4.024288119921593
            },
            {
                "id": 18,
                "x": 92.1138334584921,
                "y": 12.442424140746189
            },
            {
                "id": 19,
                "x": 62.00342912259106,
                "y": 96.67452413841833
            },
            {
                "id": 20,
                "x": 59.79715991950243,
                "y": 94.72672645496574
            },
            {
                "id": 21,
                "x": 56.19068779583755,
                "y": 60.72870720131669
            },
            {
                "id": 22,
                "x": 24.91192477692683,
                "y": 61.19348228369847
            },
            {
                "id": 23,
                "x": 26.43568328085276,
                "y": 46.56313069248718
            },
            {
                "id": 24,
                "x": 11.387895323393582,
                "y": 6.271589031088021
            },
            {
                "id": 25,
                "x": 90.94068451778354,
                "y": 48.35032839736597
            },
            {
                "id": 26,
                "x": 70.73145863544363,
                "y": 93.79035760956069
            },
            {
                "id": 27,
                "x": 87.47187556178699,
                "y": 1.3189233065599715
            },
            {
                "id": 28,
                "x": 18.051243880984746,
                "y": 9.906114358346308
            },
            {
                "id": 29,
                "x": 33.34768088451337,
                "y": 13.091307375588856
            },
            {
                "id": 30,
                "x": 78.0143379687814,
                "y": 26.477193163463486
            },
            {
                "id": 31,
                "x": 86.91318723314919,
                "y": 95.41914699326367
            },
            {
                "id": 32,
                "x": 9.604418321530728,
                "y": 34.59525741100482
            },
            {
                "id": 33,
                "x": 15.673497383298162,
                "y": 37.961536435399836
            },
            {
                "id": 34,
                "x": 88.89484936468564,
                "y": 71.68325132359816
            },
            {
                "id": 35,
                "x": 79.11634351161084,
                "y": 29.85558566296439
            },
            {
                "id": 36,
                "x": 44.47431049057135,
                "y": 58.14425720456935
            },
            {
                "id": 37,
                "x": 27.230340807583865,
                "y": 81.37340118061095
            },
            {
                "id": 38,
                "x": 69.78077897108058,
                "y": 38.523399875275324
            },
            {
                "id": 39,
                "x": 46.930269759396026,
                "y": 45.334530391614095
            },
            {
                "id": 40,
                "x": 23.416877958585935,
                "y": 41.62712876720106
            },
            {
                "id": 41,
                "x": 34.88156389932004,
                "y": 60.78573040037699
            },
            {
                "id": 42,
                "x": 38.84553058486991,
                "y": 84.35402915494575
            },
            {
                "id": 43,
                "x": 99.12097916631392,
                "y": 73.56724007288427
            },
            {
                "id": 44,
                "x": 52.741377369014664,
                "y": 54.99488275195644
            },
            {
                "id": 45,
                "x": 41.8545918298103,
                "y": 18.445216764253068
            },
            {
                "id": 46,
                "x": 64.33119894991555,
                "y": 38.88538954873827
            },
            {
                "id": 47,
                "x": 93.18860740884841,
                "y": 91.44398200596261
            },
            {
                "id": 48,
                "x": 1.5582029550835763,
                "y": 70.20237327201306
            },
            {
                "id": 49,
                "x": 42.147667724482254,
                "y": 28.985863043223503
            },
            {
                "id": 50,
                "x": 94.8360814735957,
                "y": 53.6400749277808
            },
            {
                "id": 51,
                "x": 57.07185040735978,
                "y": 67.64574627975199
            }
        ],
        "edges": [
            {
                "source": 0,
                "target": 34,
                "weight": 5.45641700360247
            },
            {
                "source": 0,
                "target": 43,
                "weight": 6.7530946840766335
            },
            {
                "source": 0,
                "target": 1,
                "weight": 14.123132007007625
            },
            {
                "source": 0,
                "target": 47,
                "weight": 15.842648512035904
            },
            {
                "source": 1,
                "target": 14,
                "weight": 4.642619700827801
            },
            {
                "source": 1,
                "target": 34,
                "weight": 9.76466105991468
            },
            {
                "source": 1,
                "target": 50,
                "weight": 10.020082743558438
            },
            {
                "source": 1,
                "target": 16,
                "weight": 11.619397769320862
            },
            {
                "source": 1,
                "target": 25,
                "weight": 13.684407229894093
            },
            {
                "source": 1,
                "target": 43,
                "weight": 15.298737392386704
            },
            {
                "source": 2,
                "target": 27,
                "weight": 19.90658797494281
            },
            {
                "source": 2,
                "target": 17,
                "weight": 20.880028497427347
            },
            {
                "source": 2,
                "target": 18,
                "weight": 27.322675288581152
            },
            {
                "source": 3,
                "target": 18,
                "weight": 12.700910443909228
            },
            {
                "source": 3,
                "target": 35,
                "weight": 16.36123467278586
            },
            {
                "source": 3,
                "target": 30,
                "weight": 16.763898517975324
            },
            {
                "source": 3,
                "target": 27,
                "weight": 24.642408736444473
            },
            {
                "source": 4,
                "target": 9,
                "weight": 1.2888529912908693
            },
            {
                "source": 4,
                "target": 37,
                "weight": 8.162965244219427
            },
            {
                "source": 4,
                "target": 42,
                "weight": 9.532989814059542
            },
            {
                "source": 5,
                "target": 29,
                "weight": 6.610307282390256
            },
            {
                "source": 5,
                "target": 28,
                "weight": 13.534535593794843
            },
            {
                "source": 5,
                "target": 45,
                "weight": 15.741395639600416
            },
            {
                "source": 5,
                "target": 11,
                "weight": 19.443013503470816
            },
            {
                "source": 5,
                "target": 17,
                "weight": 16.038406526719715
            },
            {
                "source": 5,
                "target": 24,
                "weight": 19.851260230954942
            },
            {
                "source": 6,
                "target": 42,
                "weight": 10.902559912029528
            },
            {
                "source": 6,
                "target": 20,
                "weight": 14.268762242717125
            },
            {
                "source": 6,
                "target": 19,
                "weight": 16.79011797436265
            },
            {
                "source": 7,
                "target": 21,
                "weight": 6.141520551926033
            },
            {
                "source": 7,
                "target": 51,
                "weight": 9.836821589407437
            },
            {
                "source": 7,
                "target": 44,
                "weight": 10.306373864490572
            },
            {
                "source": 7,
                "target": 16,
                "weight": 15.655568681990323
            },
            {
                "source": 8,
                "target": 31,
                "weight": 1.6445839738122687
            },
            {
                "source": 8,
                "target": 47,
                "weight": 7.340542305788524
            },
            {
                "source": 8,
                "target": 26,
                "weight": 15.541654378426236
            },
            {
                "source": 9,
                "target": 37,
                "weight": 8.971604684541717
            },
            {
                "source": 9,
                "target": 42,
                "weight": 10.664985070516884
            },
            {
                "source": 10,
                "target": 41,
                "weight": 3.23649269652834
            },
            {
                "source": 10,
                "target": 13,
                "weight": 5.969181448976679
            },
            {
                "source": 10,
                "target": 36,
                "weight": 6.751062685061801
            },
            {
                "source": 10,
                "target": 22,
                "weight": 13.062414956668352
            },
            {
                "source": 10,
                "target": 39,
                "weight": 16.850737024832306
            },
            {
                "source": 11,
                "target": 24,
                "weight": 0.9035259533250878
            },
            {
                "source": 11,
                "target": 28,
                "weight": 6.869251969712877
            },
            {
                "source": 12,
                "target": 48,
                "weight": 5.332840023482275
            },
            {
                "source": 12,
                "target": 15,
                "weight": 6.394066534629259
            },
            {
                "source": 12,
                "target": 22,
                "weight": 20.40990518236696
            },
            {
                "source": 13,
                "target": 41,
                "weight": 4.546353458652687
            },
            {
                "source": 13,
                "target": 22,
                "weight": 8.729509667493131
            },
            {
                "source": 13,
                "target": 23,
                "weight": 11.99539111639237
            },
            {
                "source": 14,
                "target": 50,
                "weight": 6.319560684893221
            },
            {
                "source": 14,
                "target": 25,
                "weight": 9.043442788679208
            },
            {
                "source": 14,
                "target": 16,
                "weight": 12.138345898227682
            },
            {
                "source": 15,
                "target": 48,
                "weight": 1.063573895490847
            },
            {
                "source": 15,
                "target": 22,
                "weight": 25.949422693477757
            },
            {
                "source": 17,
                "target": 45,
                "weight": 15.318993176924259
            },
            {
                "source": 17,
                "target": 29,
                "weight": 16.40775460560482
            },
            {
                "source": 18,
                "target": 27,
                "weight": 12.053217160697153
            },
            {
                "source": 18,
                "target": 30,
                "weight": 19.893981868529917
            },
            {
                "source": 19,
                "target": 20,
                "weight": 2.943049373041612
            },
            {
                "source": 19,
                "target": 26,
                "weight": 9.192220392451885
            },
            {
                "source": 20,
                "target": 26,
                "weight": 10.974318886567797
            },
            {
                "source": 21,
                "target": 44,
                "weight": 6.691373942373152
            },
            {
                "source": 21,
                "target": 51,
                "weight": 6.9729389184579675
            },
            {
                "source": 22,
                "target": 41,
                "weight": 9.977974034297016
            },
            {
                "source": 22,
                "target": 48,
                "weight": 25.031109439482975
            },
            {
                "source": 23,
                "target": 40,
                "weight": 5.7859571878968135
            },
            {
                "source": 23,
                "target": 33,
                "weight": 13.777230093784492
            },
            {
                "source": 23,
                "target": 32,
                "weight": 20.65239625352276
            },
            {
                "source": 24,
                "target": 28,
                "weight": 7.590124396505909
            },
            {
                "source": 25,
                "target": 50,
                "weight": 6.569287312896764
            },
            {
                "source": 26,
                "target": 31,
                "weight": 16.263495788614
            },
            {
                "source": 28,
                "target": 29,
                "weight": 15.624546059326349
            },
            {
                "source": 29,
                "target": 45,
                "weight": 10.051461564033337
            },
            {
                "source": 29,
                "target": 49,
                "weight": 18.16801222630484
            },
            {
                "source": 30,
                "target": 35,
                "weight": 3.553582994262377
            },
            {
                "source": 30,
                "target": 38,
                "weight": 14.591181923076718
            },
            {
                "source": 30,
                "target": 46,
                "weight": 18.471373282600172
            },
            {
                "source": 31,
                "target": 47,
                "weight": 7.428514996810406
            },
            {
                "source": 32,
                "target": 33,
                "weight": 6.940140857941265
            },
            {
                "source": 32,
                "target": 40,
                "weight": 15.499395342895554
            },
            {
                "source": 33,
                "target": 40,
                "weight": 8.567176307086479
            },
            {
                "source": 34,
                "target": 43,
                "weight": 10.398227941682498
            },
            {
                "source": 35,
                "target": 38,
                "weight": 12.7390646638419
            },
            {
                "source": 35,
                "target": 46,
                "weight": 17.32448723413668
            },
            {
                "source": 36,
                "target": 44,
                "weight": 8.846635191722635
            },
            {
                "source": 36,
                "target": 41,
                "weight": 9.949782299534688
            },
            {
                "source": 36,
                "target": 39,
                "weight": 13.043037872852729
            },
            {
                "source": 37,
                "target": 42,
                "weight": 11.991529372175904
            },
            {
                "source": 38,
                "target": 46,
                "weight": 5.461589414334887
            },
            {
                "source": 39,
                "target": 44,
                "weight": 11.273481244785904
            },
            {
                "source": 39,
                "target": 49,
                "weight": 17.033854710331834
            },
            {
                "source": 44,
                "target": 51,
                "weight": 13.371512432583746
            },
            {
                "source": 45,
                "target": 49,
                "weight": 10.544719885251151
            }
        ]
    },
    "configuration": {
        "start_node": 11,
        "extraction_nodes": [
            16,
            4
        ]
    }
}